moonpies/__init__.py
moonpies/_version.py
moonpies/cli.py
moonpies/config.py
moonpies/data/.moonpies.mplstyle
moonpies/data/__init__.py
moonpies/data/bahcall_etal_2001_t2.csv
moonpies/data/ballistic_hop_coldtraps.csv
moonpies/data/ballistic_sed_frac_melted_mean.csv
moonpies/data/ballistic_sed_frac_melted_std.csv
moonpies/data/basin_list.csv
moonpies/data/crater_list.csv
moonpies/data/horz_etal_1983_table2_fig19.csv
moonpies/data/needham_kring_2017_s3.csv
moonpies/moonpies.py
moonpies/plotting.py
moonpies/thermal_eq.py
moonpies-1.1.1.dist-info/LICENSE
moonpies-1.1.1.dist-info/METADATA
moonpies-1.1.1.dist-info/WHEEL
moonpies-1.1.1.dist-info/entry_points.txt
moonpies-1.1.1.dist-info/RECORD
