Metadata-Version: 2.3
Name: moonpies
Version: 1.1.1
Summary: Moon Polar Ice and Ejecta Stratigraphy model
License: MIT
Author: Christian J. Tai Udovicic
Author-email: cjtu@nau.edu
Requires-Python: >=3.8,<3.12
Classifier: Intended Audience :: Science/Research
Classifier: License :: OSI Approved :: MIT License
Classifier: Natural Language :: English
Classifier: Operating System :: OS Independent
Classifier: Programming Language :: Python :: 3
Classifier: Programming Language :: Python :: 3.8
Classifier: Programming Language :: Python :: 3.9
Classifier: Programming Language :: Python :: 3.10
Classifier: Programming Language :: Python :: 3.11
Classifier: Topic :: Scientific/Engineering :: Astronomy
Requires-Dist: matplotlib (>=3.3,<4.0)
Requires-Dist: numpy (>=1.17,<2.0)
Requires-Dist: pandas (>=1.0,<2.0)
Requires-Dist: scipy (>=1.9.1,<2.0.0)
Project-URL: Bug Tracker, https://github.com/cjtu/moonpies/issues
Project-URL: Repository, https://github.com/cjtu/moonpies
